flagai/__init__.py
flagai/env_args.py
flagai/env_trainer.py
flagai/env_trainer_v1.py
flagai/launch.py
flagai/logger.py
flagai/metrics.py
flagai/mp_tools.py
flagai/mp_utils.py
flagai/optimizers.py
flagai/schedulers.py
flagai/test_utils.py
flagai/trainer.py
flagai/trainer_v1.py
flagai/utils.py
flagai/auto_model/__init__.py
flagai/auto_model/auto_loader.py
flagai/data/__init__.py
flagai/data/collate_utils.py
flagai/data/file_utils.py
flagai/data/dataset/__init__.py
flagai/data/dataset/data_utils.py
flagai/data/dataset/block/__init__.py
flagai/data/dataset/block/blocklm_utils.py
flagai/data/dataset/block/corpora.py
flagai/data/dataset/block/data_utils.py
flagai/data/dataset/block/dataset.py
flagai/data/dataset/block/lazy_loader.py
flagai/data/dataset/cpm3_data/__init__.py
flagai/data/dataset/cpm3_data/dataset.py
flagai/data/dataset/cpm3_data/distributed_indexed.py
flagai/data/dataset/cpm3_data/indexed.py
flagai/data/dataset/data_collator/__init__.py
flagai/data/dataset/data_collator/collate_fn.py
flagai/data/dataset/indexed_dataset/__init__.py
flagai/data/dataset/indexed_dataset/build_datasets.py
flagai/data/dataset/indexed_dataset/build_index_mappings.py
flagai/data/dataset/indexed_dataset/check_datasets.py
flagai/data/dataset/indexed_dataset/merge_datasets.py
flagai/data/dataset/indexed_dataset/preprocess_data_args.py
flagai/data/dataset/language_model/__init__.py
flagai/data/dataset/language_model/dataset.py
flagai/data/dataset/mm/__init__.py
flagai/data/dataset/mm/clip_dataset.py
flagai/data/dataset/seq2seq/__init__.py
flagai/data/dataset/seq2seq/dataset.py
flagai/data/dataset/superglue/__init__.py
flagai/data/dataset/superglue/control.py
flagai/data/dataset/superglue/dataset.py
flagai/data/dataset/superglue/processor.py
flagai/data/dataset/superglue/properties.py
flagai/data/dataset/superglue/pvp.py
flagai/data/tokenizer/__init__.py
flagai/data/tokenizer/tokenizer.py
flagai/data/tokenizer/wp_tokenizer.py
flagai/data/tokenizer/bert/__init__.py
flagai-1.8.4.dist-info/LICENSE
flagai-1.8.4.dist-info/METADATA
flagai-1.8.4.dist-info/WHEEL
flagai-1.8.4.dist-info/top_level.txt
flagai-1.8.4.dist-info/RECORD
