Metadata-Version: 2.1
Name: flagai
Version: 1.8.4
Summary: FlagAI aims to help researchers and developers to freely train and test large-scale models for NLP/CV/VL tasks.
Home-page: https://github.com/FlagAI-Open/FlagAI
Author: FlagAI-Open
Author-email: open@baai.ac.cn
License: Apache 2.0
Requires-Python: >=3.8
License-File: LICENSE
Requires-Dist: nltk >=3.6.7
Requires-Dist: sentencepiece >=0.1.96
Requires-Dist: boto3 >=1.17.32
Requires-Dist: pandas >=1.3.5
Requires-Dist: jieba >=0.42.1
Requires-Dist: scikit-learn >=1.0.2
Requires-Dist: tensorboard >=2.9.0
Requires-Dist: transformers >=4.31.0
Requires-Dist: datasets >=2.0.0
Requires-Dist: setuptools >=66.0.0
Requires-Dist: protobuf >=3.19.6
Requires-Dist: ftfy
Requires-Dist: Pillow >=9.3.0
Requires-Dist: einops >=0.3.0
Requires-Dist: diffusers >=0.7.2
Requires-Dist: pytorch-lightning >=1.6.5
Requires-Dist: taming-transformers-rom1504 ==0.0.6
Requires-Dist: rouge-score
Requires-Dist: sacrebleu >=2.3.1
Requires-Dist: jsonlines
Requires-Dist: accelerate
Requires-Dist: PyYAML >=5.4.1
Requires-Dist: safetensors
Requires-Dist: timm
